simplevibe/__init__.py
simplevibe/api.py
simplevibe/cli.py
simplevibe/core.py
simplevibe/vibe_source.py
simplevibe-0.1.2.dist-info/licenses/LICENSE
simplevibe-0.1.2.dist-info/METADATA
simplevibe-0.1.2.dist-info/WHEEL
simplevibe-0.1.2.dist-info/entry_points.txt
simplevibe-0.1.2.dist-info/top_level.txt
simplevibe-0.1.2.dist-info/RECORD
