Metadata-Version: 2.4
Name: simplevibe
Version: 0.1.2
Summary: A Python library that interfaces with Llama LLM for various operations
Home-page: https://github.com/bomxacalaka/simplevibe
Author: bomxacalaka
Author-email: jorgeeduardodsc@gmail.com
Project-URL: Bug Tracker, https://github.com/bomxacalaka/simplevibe/issues
Classifier: Programming Language :: Python :: 3
Classifier: Programming Language :: Python :: 3.7
Classifier: Programming Language :: Python :: 3.8
Classifier: Programming Language :: Python :: 3.9
Classifier: Programming Language :: Python :: 3.10
Classifier: License :: OSI Approved :: MIT License
Classifier: Operating System :: OS Independent
Classifier: Intended Audience :: Developers
Classifier: Topic :: Software Development :: Libraries :: Python Modules
Requires-Python: >=3.7
License-File: LICENSE
Requires-Dist: pillow==10.4.0
Requires-Dist: requests>=2.25.0
Provides-Extra: local
Requires-Dist: transformers==4.52.3; extra == "local"
Requires-Dist: torch==2.6.0; extra == "local"
Requires-Dist: accelerate==1.3.0; extra == "local"
Requires-Dist: bitsandbytes==0.45.5; extra == "local"
Dynamic: license-file
